MANIFEST.in
README.rst
devops.py
requirements.txt
setup.py
dapper_devops.egg-info/PKG-INFO
dapper_devops.egg-info/SOURCES.txt
dapper_devops.egg-info/dependency_links.txt
dapper_devops.egg-info/not-zip-safe
dapper_devops.egg-info/requires.txt
dapper_devops.egg-info/top_level.txt