Metadata-Version: 1.1
Name: dapper-devops
Version: 0.1.6
Summary: Fabric deployment script.
Home-page: https://github.com/radiosilence/devops
Author: James Cleveland
Author-email: james@dapperdogstudios.com
License: UNKNOWN
Platform: UNKNOWN
Classifier: Environment :: Web Environment
Classifier: Intended Audience :: Developers
Classifier: License :: OSI Approved :: BSD License
Classifier: Operating System :: OS Independent
Classifier: Programming Language :: Python
Classifier: Framework :: Django
